// class version 64.0 (64)
// access flags 0x21
public class main {

  // compiled from: main.java

  // access flags 0x1
  public <init>()V
   L0
    LINENUMBER 1 L0
    ALOAD 0
    INVOKESPECIAL java/lang/Object.<init> ()V
    RETURN
   L1
    LOCALVARIABLE this Lmain; L0 L1 0
    MAXSTACK = 1
    MAXLOCALS = 1

  // access flags 0x9
  public static bubbleSort([I)V
   L0
    LINENUMBER 3 L0
    ALOAD 0
    ARRAYLENGTH
    ISTORE 1
   L1
    LINENUMBER 4 L1
    ICONST_0
    ISTORE 2
   L2
   FRAME APPEND [I I]
    ILOAD 2
    ILOAD 1
    ICONST_1
    ISUB
    IF_ICMPGE L3
   L4
    LINENUMBER 5 L4
    ICONST_0
    ISTORE 3
   L5
   FRAME APPEND [I]
    ILOAD 3
    ILOAD 1
    ILOAD 2
    ISUB
    ICONST_1
    ISUB
    IF_ICMPGE L6
   L7
    LINENUMBER 6 L7
    ALOAD 0
    ILOAD 3
    IALOAD
    ALOAD 0
    ILOAD 3
    ICONST_1
    IADD
    IALOAD
    IF_ICMPLE L8
   L9
    LINENUMBER 7 L9
    ALOAD 0
    ILOAD 3
    IALOAD
    ISTORE 4
   L10
    LINENUMBER 8 L10
    ALOAD 0
    ILOAD 3
    ALOAD 0
    ILOAD 3
    ICONST_1
    IADD
    IALOAD
    IASTORE
   L11
    LINENUMBER 9 L11
    ALOAD 0
    ILOAD 3
    ICONST_1
    IADD
    ILOAD 4
    IASTORE
   L8
    LINENUMBER 5 L8
   FRAME SAME
    IINC 3 1
    GOTO L5
   L6
    LINENUMBER 4 L6
   FRAME CHOP 1
    IINC 2 1
    GOTO L2
   L3
    LINENUMBER 13 L3
   FRAME CHOP 1
    RETURN
   L12
    LOCALVARIABLE temp I L10 L8 4
    LOCALVARIABLE j I L5 L6 3
    LOCALVARIABLE i I L2 L3 2
    LOCALVARIABLE array [I L0 L12 0
    LOCALVARIABLE n I L1 L12 1
    MAXSTACK = 5
    MAXLOCALS = 5

  // access flags 0x9
  public static main([Ljava/lang/String;)V throws java/lang/Exception
   L0
    LINENUMBER 15 L0
    RETURN
   L1
    LOCALVARIABLE args [Ljava/lang/String; L0 L1 0
    MAXSTACK = 0
    MAXLOCALS = 1
}
